rsqlalchemy/__init__.py
rsqlalchemy/parse.py
rsqlalchemy/utils.py
rsqlalchemy-0.0.1.dist-info/METADATA
rsqlalchemy-0.0.1.dist-info/WHEEL
rsqlalchemy-0.0.1.dist-info/licenses/LICENSE
rsqlalchemy-0.0.1.dist-info/RECORD
